setup.cfg
setup.py
lisa_translation_plugin/__init__.py
lisa_translation_plugin.egg-info/PKG-INFO
lisa_translation_plugin.egg-info/SOURCES.txt
lisa_translation_plugin.egg-info/dependency_links.txt
lisa_translation_plugin.egg-info/entry_points.txt
lisa_translation_plugin.egg-info/top_level.txt